src/bootstrap.py
src/main.py
src/runtime.py
src/schemas.py
src/validator_registry.py
src/validators.py
src/config/config.yaml
src/managers/client_manager.py
src/managers/connection_manager.py
src/managers/device_manager.py
src/managers/firewall_manager.py
src/managers/network_manager.py
src/managers/qos_manager.py
src/managers/stats_manager.py
src/managers/system_manager.py
src/managers/vpn_manager.py
src/tools/clients.py
src/tools/config.py
src/tools/devices.py
src/tools/firewall.py
src/tools/network.py
src/tools/port_forwards.py
src/tools/qos.py
src/tools/stats.py
src/tools/system.py
src/tools/traffic_routes.py
src/tools/vpn.py
src/utils/permissions.py
src/utils/tool_loader.py
mseep_unifi_network_mcp-0.1.4.dist-info/METADATA
mseep_unifi_network_mcp-0.1.4.dist-info/WHEEL
mseep_unifi_network_mcp-0.1.4.dist-info/entry_points.txt
mseep_unifi_network_mcp-0.1.4.dist-info/licenses/LICENSE
mseep_unifi_network_mcp-0.1.4.dist-info/RECORD
