Metadata-Version: 2.4
Name: mseep-unifi-network-mcp
Version: 0.1.4
Summary: Unifi Network MCP Server
Author-email: mseep <support@skydeck.ai>
License-File: LICENSE
Requires-Python: >=3.13
Requires-Dist: aiohttp>=3.8.5
Requires-Dist: aiounifi>=83.0.0
Requires-Dist: jsonschema>=4.17.0
Requires-Dist: mcp[cli]>=1.6.0
Requires-Dist: omegaconf>=2.3.0
Requires-Dist: python-dotenv>=1.0.0
Requires-Dist: pyyaml>=6.0
Requires-Dist: typing-extensions>=4.4.0
